{
  "mode": "hhcw",
  "tungsura": {
    "chart": {
      "1001492": 6079,
      "1001493": 3311,
      "1001494": 2949,
      "1001495": 2238,
      "progres": {
        "total": 98,
        "persen": 54.08,
        "progres": 53
      }
    },
    "table": {
      "921101": {
        "psu": "Reguler",
        "1001492": 3808,
        "1001493": 2121,
        "1001494": 1220,
        "1001495": 524,
        "progres": {
          "total": 40,
          "persen": 62.5,
          "progres": 25
        },
        "status_progress": true
      },
      "921102": {
        "psu": "Reguler",
        "1001492": 1460,
        "1001493": 577,
        "1001494": 1357,
        "1001495": 208,
        "progres": {
          "total": 18,
          "persen": 77.78,
          "progres": 14
        },
        "status_progress": true
      },
      "921103": {
        "psu": "Reguler",
        "progres": {
          "total": 11,
          "persen": 0.0,
          "progres": 0
        },
        "status_progress": false
      },
      "921104": {
        "psu": "Reguler",
        "1001492": 53,
        "1001493": 23,
        "1001494": 10,
        "1001495": 908,
        "progres": {
          "total": 12,
          "persen": 41.67,
          "progres": 5
        },
        "status_progress": true
      },
      "921105": {
        "psu": "Reguler",
        "1001492": 638,
        "1001493": 486,
        "1001494": 288,
        "1001495": 515,
        "progres": {
          "total": 12,
          "persen": 50.0,
          "progres": 6
        },
        "status_progress": true
      },
      "921106": {
        "psu": "Reguler",
        "1001492": 120,
        "1001493": 104,
        "1001494": 74,
        "1001495": 83,
        "progres": {
          "total": 5,
          "persen": 60.0,
          "progres": 3
        },
        "status_progress": true
      }
    }
  },
  "psu": "Reguler",
  "progres": {
    "total": 98,
    "progres": 53
  },
  "ts": "2024-11-28 09:45:00"
}