{
  "mode": "hhcw",
  "tungsura": {
    "chart": {
      "1000112": 0,
      "1000113": 0,
      "1000114": 0,
      "1000115": 0,
      "progres": {
        "total": 766,
        "persen": 94.13,
        "progres": 721
      }
    },
    "table": {
      "110301": {
        "psu": "Reguler",
        "1000112": 0,
        "1000113": 0,
        "1000114": 0,
        "1000115": 0,
        "progres": {
          "total": 50,
          "persen": 98.0,
          "progres": 49
        },
        "status_progress": true
      },
      "110302": {
        "psu": "Reguler",
        "1000112": 0,
        "1000113": 0,
        "1000114": 0,
        "1000115": 0,
        "progres": {
          "total": 49,
          "persen": 100.0,
          "progres": 49
        },
        "status_progress": true
      },
      "110303": {
        "psu": "Reguler",
        "1000112": 0,
        "1000113": 0,
        "1000114": 0,
        "1000115": 0,
        "progres": {
          "total": 66,
          "persen": 78.79,
          "progres": 52
        },
        "status_progress": true
      },
      "110304": {
        "psu": "Reguler",
        "1000112": 0,
        "1000113": 0,
        "1000114": 0,
        "1000115": 0,
        "progres": {
          "total": 46,
          "persen": 95.65,
          "progres": 44
        },
        "status_progress": true
      },
      "110305": {
        "psu": "Reguler",
        "1000112": 0,
        "1000113": 0,
        "1000114": 0,
        "1000115": 0,
        "progres": {
          "total": 19,
          "persen": 100.0,
          "progres": 19
        },
        "status_progress": true
      },
      "110306": {
        "psu": "Reguler",
        "1000112": 0,
        "1000113": 0,
        "1000114": 0,
        "1000115": 0,
        "progres": {
          "total": 36,
          "persen": 100.0,
          "progres": 36
        },
        "status_progress": true
      },
      "110307": {
        "psu": "Reguler",
        "1000112": 0,
        "1000113": 0,
        "1000114": 0,
        "1000115": 0,
        "progres": {
          "total": 73,
          "persen": 95.89,
          "progres": 70
        },
        "status_progress": true
      },
      "110308": {
        "psu": "Reguler",
        "1000112": 0,
        "1000113": 0,
        "1000114": 0,
        "1000115": 0,
        "progres": {
          "total": 22,
          "persen": 86.36,
          "progres": 19
        },
        "status_progress": true
      },
      "110309": {
        "psu": "Reguler",
        "1000112": 0,
        "1000113": 0,
        "1000114": 0,
        "1000115": 0,
        "progres": {
          "total": 35,
          "persen": 88.57,
          "progres": 31
        },
        "status_progress": true
      },
      "110310": {
        "psu": "Reguler",
        "1000112": 0,
        "1000113": 0,
        "1000114": 0,
        "1000115": 0,
        "progres": {
          "total": 41,
          "persen": 100.0,
          "progres": 41
        },
        "status_progress": true
      },
      "110311": {
        "psu": "Reguler",
        "1000112": 0,
        "1000113": 0,
        "1000114": 0,
        "1000115": 0,
        "progres": {
          "total": 43,
          "persen": 90.7,
          "progres": 39
        },
        "status_progress": true
      },
      "110312": {
        "psu": "Reguler",
        "1000112": 0,
        "1000113": 0,
        "1000114": 0,
        "1000115": 0,
        "progres": {
          "total": 45,
          "persen": 93.33,
          "progres": 42
        },
        "status_progress": true
      },
      "110313": {
        "psu": "Reguler",
        "1000112": 0,
        "1000113": 0,
        "1000114": 0,
        "1000115": 0,
        "progres": {
          "total": 27,
          "persen": 92.59,
          "progres": 25
        },
        "status_progress": true
      },
      "110314": {
        "psu": "Reguler",
        "1000112": 0,
        "1000113": 0,
        "1000114": 0,
        "1000115": 0,
        "progres": {
          "total": 28,
          "persen": 100.0,
          "progres": 28
        },
        "status_progress": true
      },
      "110315": {
        "psu": "Reguler",
        "1000112": 0,
        "1000113": 0,
        "1000114": 0,
        "1000115": 0,
        "progres": {
          "total": 18,
          "persen": 94.44,
          "progres": 17
        },
        "status_progress": true
      },
      "110316": {
        "psu": "Reguler",
        "1000112": 0,
        "1000113": 0,
        "1000114": 0,
        "1000115": 0,
        "progres": {
          "total": 24,
          "persen": 91.67,
          "progres": 22
        },
        "status_progress": true
      },
      "110317": {
        "psu": "Reguler",
        "1000112": 0,
        "1000113": 0,
        "1000114": 0,
        "1000115": 0,
        "progres": {
          "total": 27,
          "persen": 92.59,
          "progres": 25
        },
        "status_progress": true
      },
      "110318": {
        "psu": "Reguler",
        "1000112": 0,
        "1000113": 0,
        "1000114": 0,
        "1000115": 0,
        "progres": {
          "total": 27,
          "persen": 100.0,
          "progres": 27
        },
        "status_progress": true
      },
      "110319": {
        "psu": "Reguler",
        "1000112": 0,
        "1000113": 0,
        "1000114": 0,
        "1000115": 0,
        "progres": {
          "total": 22,
          "persen": 100.0,
          "progres": 22
        },
        "status_progress": true
      },
      "110320": {
        "psu": "Reguler",
        "1000112": 0,
        "1000113": 0,
        "1000114": 0,
        "1000115": 0,
        "progres": {
          "total": 8,
          "persen": 62.5,
          "progres": 5
        },
        "status_progress": true
      },
      "110321": {
        "psu": "Reguler",
        "1000112": 0,
        "1000113": 0,
        "1000114": 0,
        "1000115": 0,
        "progres": {
          "total": 18,
          "persen": 100.0,
          "progres": 18
        },
        "status_progress": true
      },
      "110322": {
        "psu": "Reguler",
        "1000112": 0,
        "1000113": 0,
        "1000114": 0,
        "1000115": 0,
        "progres": {
          "total": 11,
          "persen": 100.0,
          "progres": 11
        },
        "status_progress": true
      },
      "110323": {
        "psu": "Reguler",
        "1000112": 0,
        "1000113": 0,
        "1000114": 0,
        "1000115": 0,
        "progres": {
          "total": 15,
          "persen": 93.33,
          "progres": 14
        },
        "status_progress": true
      },
      "110324": {
        "psu": "Reguler",
        "1000112": 0,
        "1000113": 0,
        "1000114": 0,
        "1000115": 0,
        "progres": {
          "total": 16,
          "persen": 100.0,
          "progres": 16
        },
        "status_progress": true
      }
    }
  },
  "psu": "Reguler",
  "progres": {
    "total": 766,
    "progres": 721
  },
  "ts": "2024-11-28 10:45:04"
}