{
  "mode": "hhcw",
  "tungsura": {
    "chart": {
      "1000045": 0,
      "1000046": 0,
      "1000047": 0,
      "progres": {
        "total": 527,
        "persen": 91.08,
        "progres": 480
      }
    },
    "table": {
      "611001": {
        "psu": "Reguler",
        "1000045": 0,
        "1000046": 0,
        "1000047": 0,
        "progres": {
          "total": 53,
          "persen": 98.11,
          "progres": 52
        },
        "status_progress": true
      },
      "611002": {
        "psu": "Reguler",
        "1000045": 0,
        "1000046": 0,
        "1000047": 0,
        "progres": {
          "total": 89,
          "persen": 100.0,
          "progres": 89
        },
        "status_progress": true
      },
      "611003": {
        "psu": "Reguler",
        "1000045": 0,
        "1000046": 0,
        "1000047": 0,
        "progres": {
          "total": 57,
          "persen": 87.72,
          "progres": 50
        },
        "status_progress": true
      },
      "611004": {
        "psu": "Reguler",
        "1000045": 0,
        "1000046": 0,
        "1000047": 0,
        "progres": {
          "total": 61,
          "persen": 88.52,
          "progres": 54
        },
        "status_progress": true
      },
      "611005": {
        "psu": "Reguler",
        "1000045": 0,
        "1000046": 0,
        "1000047": 0,
        "progres": {
          "total": 45,
          "persen": 93.33,
          "progres": 42
        },
        "status_progress": true
      },
      "611006": {
        "psu": "Reguler",
        "1000045": 0,
        "1000046": 0,
        "1000047": 0,
        "progres": {
          "total": 38,
          "persen": 94.74,
          "progres": 36
        },
        "status_progress": true
      },
      "611007": {
        "psu": "Reguler",
        "1000045": 0,
        "1000046": 0,
        "1000047": 0,
        "progres": {
          "total": 47,
          "persen": 61.7,
          "progres": 29
        },
        "status_progress": true
      },
      "611008": {
        "psu": "Reguler",
        "1000045": 0,
        "1000046": 0,
        "1000047": 0,
        "progres": {
          "total": 44,
          "persen": 100.0,
          "progres": 44
        },
        "status_progress": true
      },
      "611009": {
        "psu": "Reguler",
        "1000045": 0,
        "1000046": 0,
        "1000047": 0,
        "progres": {
          "total": 26,
          "persen": 100.0,
          "progres": 26
        },
        "status_progress": true
      },
      "611010": {
        "psu": "Reguler",
        "1000045": 0,
        "1000046": 0,
        "1000047": 0,
        "progres": {
          "total": 29,
          "persen": 96.55,
          "progres": 28
        },
        "status_progress": true
      },
      "611011": {
        "psu": "Reguler",
        "1000045": 0,
        "1000046": 0,
        "1000047": 0,
        "progres": {
          "total": 38,
          "persen": 78.95,
          "progres": 30
        },
        "status_progress": true
      }
    }
  },
  "psu": "Reguler",
  "progres": {
    "total": 527,
    "progres": 480
  },
  "ts": "2024-11-28 10:45:04"
}