{
  "mode": "hhcw",
  "tungsura": {
    "chart": {
      "1000512": 56385,
      "1000513": 37255,
      "progres": {
        "total": 235,
        "persen": 100.0,
        "progres": 235
      }
    },
    "table": {
      "187201": {
        "psu": "Reguler",
        "1000512": 16609,
        "1000513": 11273,
        "progres": {
          "total": 71,
          "persen": 100.0,
          "progres": 71
        },
        "status_progress": true
      },
      "187202": {
        "psu": "Reguler",
        "1000512": 10158,
        "1000513": 7676,
        "progres": {
          "total": 44,
          "persen": 100.0,
          "progres": 44
        },
        "status_progress": true
      },
      "187203": {
        "psu": "Reguler",
        "1000512": 9558,
        "1000513": 6129,
        "progres": {
          "total": 39,
          "persen": 100.0,
          "progres": 39
        },
        "status_progress": true
      },
      "187204": {
        "psu": "Reguler",
        "1000512": 13143,
        "1000513": 8500,
        "progres": {
          "total": 55,
          "persen": 100.0,
          "progres": 55
        },
        "status_progress": true
      },
      "187205": {
        "psu": "Reguler",
        "1000512": 6917,
        "1000513": 3677,
        "progres": {
          "total": 26,
          "persen": 100.0,
          "progres": 26
        },
        "status_progress": true
      }
    }
  },
  "psu": "Reguler",
  "progres": {
    "total": 235,
    "progres": 235
  },
  "ts": "2024-11-27 20:45:00"
}