{
  "mode": "hhcw",
  "tungsura": {
    "chart": {
      "1000079": 11398,
      "1000080": 8964,
      "1000081": 14906,
      "progres": {
        "total": 215,
        "persen": 69.3,
        "progres": 149
      }
    },
    "table": {
      "810701": {
        "psu": "Reguler",
        "1000079": 6542,
        "1000080": 3988,
        "1000081": 7951,
        "progres": {
          "total": 87,
          "persen": 83.91,
          "progres": 73
        },
        "status_progress": true
      },
      "810702": {
        "psu": "Reguler",
        "1000079": 516,
        "1000080": 473,
        "1000081": 1257,
        "progres": {
          "total": 17,
          "persen": 58.82,
          "progres": 10
        },
        "status_progress": true
      },
      "810703": {
        "psu": "Reguler",
        "1000079": 1299,
        "1000080": 1324,
        "1000081": 2322,
        "progres": {
          "total": 32,
          "persen": 75.0,
          "progres": 24
        },
        "status_progress": true
      },
      "810704": {
        "psu": "Reguler",
        "1000079": 687,
        "1000080": 929,
        "1000081": 1082,
        "progres": {
          "total": 13,
          "persen": 84.62,
          "progres": 11
        },
        "status_progress": true
      },
      "810705": {
        "psu": "Reguler",
        "1000079": 809,
        "1000080": 639,
        "1000081": 646,
        "progres": {
          "total": 9,
          "persen": 77.78,
          "progres": 7
        },
        "status_progress": true
      },
      "810706": {
        "psu": "Reguler",
        "1000079": 472,
        "1000080": 571,
        "1000081": 490,
        "progres": {
          "total": 11,
          "persen": 81.82,
          "progres": 9
        },
        "status_progress": true
      },
      "810707": {
        "psu": "Reguler",
        "1000079": 181,
        "1000080": 109,
        "1000081": 373,
        "progres": {
          "total": 15,
          "persen": 26.67,
          "progres": 4
        },
        "status_progress": true
      },
      "810708": {
        "psu": "Reguler",
        "1000079": 502,
        "1000080": 605,
        "1000081": 255,
        "progres": {
          "total": 10,
          "persen": 40.0,
          "progres": 4
        },
        "status_progress": true
      },
      "810709": {
        "psu": "Reguler",
        "1000079": 92,
        "1000080": 79,
        "1000081": 274,
        "progres": {
          "total": 11,
          "persen": 18.18,
          "progres": 2
        },
        "status_progress": true
      },
      "810710": {
        "psu": "Reguler",
        "1000079": 298,
        "1000080": 247,
        "1000081": 256,
        "progres": {
          "total": 10,
          "persen": 50.0,
          "progres": 5
        },
        "status_progress": true
      }
    }
  },
  "psu": "Reguler",
  "progres": {
    "total": 215,
    "progres": 149
  },
  "ts": "2024-11-28 10:15:04"
}