{
  "mode": "hhcw",
  "tungsura": {
    "chart": {
      "1000591": 0,
      "1000592": 0,
      "1000593": 0,
      "1000594": 0,
      "1000595": 0,
      "progres": {
        "total": 2562,
        "persen": 99.73,
        "progres": 2555
      }
    },
    "table": {
      "321701": {
        "psu": "Reguler",
        "1000591": 0,
        "1000592": 0,
        "1000593": 0,
        "1000594": 0,
        "1000595": 0,
        "progres": {
          "total": 326,
          "persen": 98.16,
          "progres": 320
        },
        "status_progress": true
      },
      "321702": {
        "psu": "Reguler",
        "1000591": 0,
        "1000592": 0,
        "1000593": 0,
        "1000594": 0,
        "1000595": 0,
        "progres": {
          "total": 144,
          "persen": 99.31,
          "progres": 143
        },
        "status_progress": true
      },
      "321703": {
        "psu": "Reguler",
        "1000591": 0,
        "1000592": 0,
        "1000593": 0,
        "1000594": 0,
        "1000595": 0,
        "progres": {
          "total": 109,
          "persen": 100.0,
          "progres": 109
        },
        "status_progress": true
      },
      "321704": {
        "psu": "Reguler",
        "1000591": 0,
        "1000592": 0,
        "1000593": 0,
        "1000594": 0,
        "1000595": 0,
        "progres": {
          "total": 183,
          "persen": 100.0,
          "progres": 183
        },
        "status_progress": true
      },
      "321705": {
        "psu": "Reguler",
        "1000591": 0,
        "1000592": 0,
        "1000593": 0,
        "1000594": 0,
        "1000595": 0,
        "progres": {
          "total": 122,
          "persen": 100.0,
          "progres": 122
        },
        "status_progress": true
      },
      "321706": {
        "psu": "Reguler",
        "1000591": 0,
        "1000592": 0,
        "1000593": 0,
        "1000594": 0,
        "1000595": 0,
        "progres": {
          "total": 241,
          "persen": 100.0,
          "progres": 241
        },
        "status_progress": true
      },
      "321707": {
        "psu": "Reguler",
        "1000591": 0,
        "1000592": 0,
        "1000593": 0,
        "1000594": 0,
        "1000595": 0,
        "progres": {
          "total": 206,
          "persen": 100.0,
          "progres": 206
        },
        "status_progress": true
      },
      "321708": {
        "psu": "Reguler",
        "1000591": 0,
        "1000592": 0,
        "1000593": 0,
        "1000594": 0,
        "1000595": 0,
        "progres": {
          "total": 251,
          "persen": 100.0,
          "progres": 251
        },
        "status_progress": true
      },
      "321709": {
        "psu": "Reguler",
        "1000591": 0,
        "1000592": 0,
        "1000593": 0,
        "1000594": 0,
        "1000595": 0,
        "progres": {
          "total": 143,
          "persen": 100.0,
          "progres": 143
        },
        "status_progress": true
      },
      "321710": {
        "psu": "Reguler",
        "1000591": 0,
        "1000592": 0,
        "1000593": 0,
        "1000594": 0,
        "1000595": 0,
        "progres": {
          "total": 188,
          "persen": 100.0,
          "progres": 188
        },
        "status_progress": true
      },
      "321711": {
        "psu": "Reguler",
        "1000591": 0,
        "1000592": 0,
        "1000593": 0,
        "1000594": 0,
        "1000595": 0,
        "progres": {
          "total": 153,
          "persen": 100.0,
          "progres": 153
        },
        "status_progress": true
      },
      "321712": {
        "psu": "Reguler",
        "1000591": 0,
        "1000592": 0,
        "1000593": 0,
        "1000594": 0,
        "1000595": 0,
        "progres": {
          "total": 133,
          "persen": 100.0,
          "progres": 133
        },
        "status_progress": true
      },
      "321713": {
        "psu": "Reguler",
        "1000591": 0,
        "1000592": 0,
        "1000593": 0,
        "1000594": 0,
        "1000595": 0,
        "progres": {
          "total": 99,
          "persen": 100.0,
          "progres": 99
        },
        "status_progress": true
      },
      "321714": {
        "psu": "Reguler",
        "1000591": 0,
        "1000592": 0,
        "1000593": 0,
        "1000594": 0,
        "1000595": 0,
        "progres": {
          "total": 107,
          "persen": 100.0,
          "progres": 107
        },
        "status_progress": true
      },
      "321715": {
        "psu": "Reguler",
        "1000591": 0,
        "1000592": 0,
        "1000593": 0,
        "1000594": 0,
        "1000595": 0,
        "progres": {
          "total": 110,
          "persen": 100.0,
          "progres": 110
        },
        "status_progress": true
      },
      "321716": {
        "psu": "Reguler",
        "1000591": 0,
        "1000592": 0,
        "1000593": 0,
        "1000594": 0,
        "1000595": 0,
        "progres": {
          "total": 47,
          "persen": 100.0,
          "progres": 47
        },
        "status_progress": true
      }
    }
  },
  "psu": "Reguler",
  "progres": {
    "total": 2562,
    "progres": 2555
  },
  "ts": "2024-11-28 10:45:04"
}